LICENSE
README.md
tres.py
tres-1.3.dist-info/LICENSE
tres-1.3.dist-info/WHEEL
tres-1.3.dist-info/METADATA
tres-1.3.dist-info/RECORD
