Metadata-Version: 2.1
Name: tres
Version: 1.3
Summary: Typed resolver (dependency container) for Python
Home-page: https://github.com/r1chardj0n3s/tres
Author: Richard Jones
Author-email: richard@mechanicalcat.net
Classifier: Programming Language :: Python :: 2
Classifier: Programming Language :: Python :: 2.7
Classifier: Programming Language :: Python :: 3
Classifier: Programming Language :: Python :: 3.4
Classifier: Programming Language :: Python :: 3.5
Classifier: Programming Language :: Python :: 3.6
Classifier: Programming Language :: Python :: 3.7
Classifier: Programming Language :: Python :: 3.8
